async4.v
`timescale 1ns/1ns
module async4 (
    input clk,        // Main clock input
    input reset,      // Asynchronous active-high reset
    output [3:0] q    // 4-bit counter output
);

    // Instantiate 4 T flip-flops
    t_ff_pos t0 (.clk(clk),  .reset(reset), .q(q[0]));    // LSB toggles on posedge of main clock
    t_ff_neg t1 (.clk(q[0]), .reset(reset), .q(q[1]));    // Next toggles on negedge of previous bit
    t_ff_neg t2 (.clk(q[1]), .reset(reset), .q(q[2]));    // Next toggles on negedge of previous bit
    t_ff_neg t3 (.clk(q[2]), .reset(reset), .q(q[3]));    // MSB toggles on negedge of previous bit

endmodule


// T flip-flop that toggles on POSITIVE edge
module t_ff_pos (
    input clk,
    input reset,
    output reg q
);
    always @(posedge clk or posedge reset) begin
        if (reset)
            q <= 1'b0;
        else
            q <= ~q;  // Toggle output
    end
endmodule


// T flip-flop that toggles on NEGATIVE edge
module t_ff_neg (
    input clk,
    input reset,
    output reg q
);
    always @(negedge clk or posedge reset) begin
        if (reset)
            q <= 1'b0;
        else
            q <= ~q;  // Toggle output
    end
endmodule

async4_tb.v
`timescale 1ns/1ns
`include "async4.v"

module async4_tb;
    reg clk, reset;
    wire [3:0] q;

    // Instantiate the counter
    async4 uut (.clk(clk), .reset(reset), .q(q));

    // Clock generation
    initial begin
        clk = 0;
        forever #20 clk = ~clk;   // Clock period = 40ns
    end

    // Stimulus block
    initial begin
        $dumpfile("async4_tb.vcd");
        $dumpvars(0, async4_tb);

        reset = 1;  #25;          // Apply reset
        reset = 0;                // Release reset

        #240;                     // Let counter run
        $display("Simulation finished successfully!");
        $finish;
    end
endmodule

async4_tb.vcd
$date
	Mon Oct 27 16:12:19 2025
$end
$version
	Icarus Verilog
$end
$timescale
	1ns
$end
$scope module async4_tb $end
$var wire 4 ! q [3:0] $end
$var reg 1 " clk $end
$var reg 1 # reset $end
$scope module uut $end
$var wire 1 " clk $end
$var wire 1 # reset $end
$var wire 4 $ q [3:0] $end
$scope module t0 $end
$var wire 1 " clk $end
$var wire 1 # reset $end
$var reg 1 % q $end
$upscope $end
$scope module t1 $end
$var wire 1 & clk $end
$var wire 1 # reset $end
$var reg 1 ' q $end
$upscope $end
$scope module t2 $end
$var wire 1 ( clk $end
$var wire 1 # reset $end
$var reg 1 ) q $end
$upscope $end
$scope module t3 $end
$var wire 1 * clk $end
$var wire 1 # reset $end
$var reg 1 + q $end
$upscope $end
$upscope $end
$upscope $end
$enddefinitions $end
#0
$dumpvars
0+
0*
0)
0(
0'
0&
0%
b0 $
1#
0"
b0 !
$end
#20
1"
#25
0#
#40
0"
#60
1&
b1 !
b1 $
1%
1"
#80
0"
#100
1(
1'
0&
b10 !
b10 $
0%
1"
#120
0"
#140
1&
b11 !
b11 $
1%
1"
#160
0"
#180
1*
1)
0(
0'
0&
b100 !
b100 $
0%
1"
#200
0"
#220
1&
b101 !
b101 $
1%
1"
#240
0"
#260
1(
1'
0&
b110 !
b110 $
0%
1"
