lab9/q1.v
module q1(E,x,clk,A,B,reset);
input E,x,clk,reset;
output A,B;
jkff ffA((E&~x&~B)|(E&x&B), (E&~x&~B)|(E&x&B), clk, A, reset);
jkff ffB(E,E,clk,B,reset);
endmodule

module jkff(J,K,clk,Q,reset);
input J,K, clk, reset;
output Q;
reg Q;
initial Q = 0; //initialize dont care otherwise when clk=0, reset=0, Q=x
always@(posedge clk)
 if(reset) Q<=0;
 else begin
  case({J,K})
    2'b00: Q<=Q;
    2'b01: Q<=0;
    2'b10: Q<=1;
    2'b11: Q<=~Q; 
   endcase end
endmodule

lab9/q1_tb.v
`timescale 1ns/1ns
`include "q1.v"
module q1_tb();
reg E,x,clk,reset;
wire A,B;
q1 e1(E,x,clk,A,B,reset);
initial begin
$dumpfile("q1_tb.vcd");
$dumpvars(0, q1_tb);
clk=0;
forever #10 clk=~clk;
end 
initial begin
 E=1; x=1; #20;
 E=1; x=1; #20;
 E=1; x=1; #20;
 E=1; x=1; #20;
 E=1; x=0; #20;
 E=1; x=0; #20;
 
$display("success"); $finish;
end 
endmodule

lab9/q1_tb.vcd
$date
	Mon Oct 13 15:22:43 2025
$end
$version
	Icarus Verilog
$end
$timescale
	1ns
$end
$scope module q1_tb $end
$var wire 1 ! B $end
$var wire 1 " A $end
$var reg 1 # E $end
$var reg 1 $ clk $end
$var reg 1 % reset $end
$var reg 1 & x $end
$scope module e1 $end
$var wire 1 # E $end
$var wire 1 $ clk $end
$var wire 1 % reset $end
$var wire 1 & x $end
$var wire 1 ! B $end
$var wire 1 " A $end
$scope module ffA $end
$var wire 1 ' J $end
$var wire 1 ( K $end
$var wire 1 $ clk $end
$var wire 1 % reset $end
$var reg 1 " Q $end
$upscope $end
$scope module ffB $end
$var wire 1 # J $end
$var wire 1 # K $end
$var wire 1 $ clk $end
$var wire 1 % reset $end
$var reg 1 ! Q $end
$upscope $end
$upscope $end
$upscope $end
$enddefinitions $end
#0
$dumpvars
0(
0'
1&
x%
0$
1#
0"
0!
$end
#10
1(
1'
1!
1$
#20
0$
#30
0(
0'
0!
1"
1$
#40
0$
#50
1(
1'
1!
1$
#60
0$
#70
0(
0'
0!
0"
1$
#80
1'
1(
0$
0&
#90
0(
0'
1"
1!
1$
#100
0$
#110
1(
1'
0!
1$
