lab9/q2.v
module q2(clk,reset,x,A,B);
input clk,reset,x;
output A,B;
tff fA(~A&B|B&~x, clk, A, reset);
tff fB(~x&A|~x&~B|x&~A&B,clk,B,reset);
endmodule


module tff(T,clk,Q,reset);
input T, clk, reset;
output Q;
reg Q;
initial Q = 0; //initialize dont care otherwise when clk=0, reset=0, Q=x
always@(posedge clk)
 if(reset) Q<=0;
 else 
  if(T==0) Q<=Q;
  else if(T==1) Q<=~Q;
endmodule

lab9/q2_tb.v
`timescale 1ns/1ns
`include "q2.v"
module q2_tb();
reg x,clk,reset;
wire A,B;
q2 e1(clk,reset,x,A,B);
initial begin
$dumpfile("q2_tb.vcd");
$dumpvars(0, q2_tb);
clk=0;
forever #10 clk=~clk;
end 
initial begin
 x=1; #20;
 x=0; #20;
 x=1; #20;
 x=1; #20;
 x=0; #20;
 x=0; #20;
 
$display("success"); $finish;
end 
endmodule

lab9/q2_tb.vcd
$date
	Mon Oct 13 15:54:15 2025
$end
$version
	Icarus Verilog
$end
$timescale
	1ns
$end
$scope module q2_tb $end
$var wire 1 ! B $end
$var wire 1 " A $end
$var reg 1 # clk $end
$var reg 1 $ reset $end
$var reg 1 % x $end
$scope module e1 $end
$var wire 1 # clk $end
$var wire 1 $ reset $end
$var wire 1 % x $end
$var wire 1 ! B $end
$var wire 1 " A $end
$scope module fA $end
$var wire 1 & T $end
$var wire 1 # clk $end
$var wire 1 $ reset $end
$var reg 1 " Q $end
$upscope $end
$scope module fB $end
$var wire 1 ' T $end
$var wire 1 # clk $end
$var wire 1 $ reset $end
$var reg 1 ! Q $end
$upscope $end
$upscope $end
$upscope $end
$enddefinitions $end
#0
$dumpvars
0'
0&
1%
x$
0#
0"
0!
$end
#10
1#
#20
1'
0#
0%
#30
0'
1&
1!
1#
#40
1'
0#
1%
#50
0'
0&
1"
0!
1#
#60
0#
#70
1#
#80
1'
0#
0%
#90
1&
1!
1#
#100
0#
#110
1'
0&
0!
0"
1#
