week8/sreg6.v
module sreg6(w, clk, q);
input w;
input clk;
output [5:0] q;   // must be a wire (default type is wire)
                   // no need for reg or initial assignment

dff s1(w,   clk, q[5]);
dff s2(q[5],clk, q[4]);
dff s3(q[4],clk, q[3]);
dff s4(q[3],clk, q[2]);
dff s5(q[2],clk, q[1]);
dff s6(q[1],clk, q[0]);
endmodule


module dff (D, Clock, Q);
input D, Clock;
output reg Q;     // reg inside the flip-flop, that's fine
initial Q=0;
always @(posedge Clock)
    Q <= D;
endmodule

week8/sreg6_tb.v
`timescale 1ns/1ns
`include "sreg6.v"
module sreg6_tb();
reg w;
reg clk;
wire [5:0]q;
sreg6 a1(w,clk, q);
initial
begin
clk=0;
forever #20 clk = ~clk;
end
initial
begin
$dumpfile("sreg6_tb.vcd");
$dumpvars(0,sreg6_tb);
w=1; #40;
w=0; #40;
w=1; #40;
w=0; #40;
w=0; #40;
w=0; #40;
$display("success");
$finish;
end
endmodule

week8/sreg6_tb.vcd
$date
	Mon Oct  6 14:40:49 2025
$end
$version
	Icarus Verilog
$end
$timescale
	1ns
$end
$scope module sreg6_tb $end
$var wire 6 ! q [5:0] $end
$var reg 1 " clk $end
$var reg 1 # w $end
$scope module a1 $end
$var wire 1 " clk $end
$var wire 1 # w $end
$var wire 6 $ q [5:0] $end
$scope module s1 $end
$var wire 1 " Clock $end
$var wire 1 # D $end
$var reg 1 % Q $end
$upscope $end
$scope module s2 $end
$var wire 1 " Clock $end
$var wire 1 & D $end
$var reg 1 ' Q $end
$upscope $end
$scope module s3 $end
$var wire 1 " Clock $end
$var wire 1 ( D $end
$var reg 1 ) Q $end
$upscope $end
$scope module s4 $end
$var wire 1 " Clock $end
$var wire 1 * D $end
$var reg 1 + Q $end
$upscope $end
$scope module s5 $end
$var wire 1 " Clock $end
$var wire 1 , D $end
$var reg 1 - Q $end
$upscope $end
$scope module s6 $end
$var wire 1 " Clock $end
$var wire 1 . D $end
$var reg 1 / Q $end
$upscope $end
$upscope $end
$upscope $end
$enddefinitions $end
#0
$dumpvars
0/
0.
0-
0,
0+
0*
0)
0(
0'
0&
0%
b0 $
1#
0"
b0 !
$end
#20
1&
b100000 !
b100000 $
1%
1"
#40
0"
0#
#60
1(
0&
1'
b10000 !
b10000 $
0%
1"
#80
0"
1#
#100
1&
0(
1*
1%
0'
b101000 !
b101000 $
1)
1"
#120
0"
0#
#140
1,
0*
1(
0&
1+
0)
1'
b10100 !
b10100 $
0%
1"
#160
0"
#180
0(
1*
0,
1.
0'
1)
0+
b1010 !
b1010 $
1-
1"
#200
0"
#220
0.
1,
0*
1/
0-
1+
b101 !
b101 $
0)
1"
