repeat/ex4.v
module ex4(a,b,c,d,f);
input a,b,c,d;
output f;
assign f=~( (~(~b&~d)) & (~(~a&d)) );
endmodule

repeat/ex4_tb.v
`timescale 1ns/1ns
`include "ex4.v"

module ex4_tb();
reg a,b,c,d; //inputs
wire f; //outputs
ex4 e(a,b,c,d,f);

initial 
begin

$dumpfile("ex4_tb.vcd"); //make sure waveform is getting stored, store inp/out waveforms
$dumpvars(0,ex4_tb); //only testbench module name- example_tb

a=1'b0; b=1'b0; c=1'b0; d=1'b0;
#10;
a=1'b0; b=1'b0; c=1'b0; d=1'b1;
#10;
a=1'b0; b=1'b0; c=1'b1; d=1'b0; //0010
#10; 
a=1'b0; b=1'b0; c=1'b1; d=1'b1;//0011
#10; 
a=1'b0; b=1'b1; c=1'b0; d=1'b0;
#10;
a=1'b0; b=1'b1; c=1'b0; d=1'b1;
#10;
a=1'b0; b=1'b1; c=1'b1; d=1'b0;
#10;
a=1'b0; b=1'b1; c=1'b1; d=1'b1;
#10;
a=1'b1; b=1'b0; c=1'b0; d=1'b0; //1000
#10;
a=1'b1; b=1'b0; c=1'b0; d=1'b1;
#10;
a=1'b1; b=1'b0; c=1'b1; d=1'b0;
#10;
a=1'b1; b=1'b0; c=1'b1; d=1'b1;
#10;
a=1'b1; b=1'b1; c=1'b0; d=1'b0;
#10;
a=1'b1; b=1'b1; c=1'b0; d=1'b1;
#10;
a=1'b1; b=1'b1; c=1'b1; d=1'b0;
#10;
a=1'b1; b=1'b1; c=1'b1; d=1'b1;
#10;

$display("Success");
end
endmodule

repeat/ex4_tb.vcd
$date
	Wed Aug 13 15:11:04 2025
$end
$version
	Icarus Verilog
$end
$timescale
	1ns
$end
$scope module ex4_tb $end
$var wire 1 ! f $end
$var reg 1 " a $end
$var reg 1 # b $end
$var reg 1 $ c $end
$var reg 1 % d $end
$scope module e $end
$var wire 1 " a $end
$var wire 1 # b $end
$var wire 1 $ c $end
$var wire 1 % d $end
$var wire 1 ! f $end
$upscope $end
$upscope $end
$enddefinitions $end
#0
$dumpvars
0%
0$
0#
0"
1!
$end
#10
1%
#20
1!
0%
1$
#30
1%
#40
0!
0%
0$
1#
#50
1!
1%
#60
0!
0%
1$
#70
1!
1%
#80
0%
0$
0#
1"
#90
0!
1%
#100
1!
0%
1$
#110
0!
1%
#120
0%
0$
1#
#130
1%
#140
0%
1$
#150
1%
